hatch_nodejs_build/__init__.py
hatch_nodejs_build/_util.py
hatch_nodejs_build/cache.py
hatch_nodejs_build/config.py
hatch_nodejs_build/hooks.py
hatch_nodejs_build/plugin.py
hatch_nodejs_build-1.1.1.dist-info/METADATA
hatch_nodejs_build-1.1.1.dist-info/WHEEL
hatch_nodejs_build-1.1.1.dist-info/entry_points.txt
hatch_nodejs_build-1.1.1.dist-info/licenses/LICENSE.md
hatch_nodejs_build-1.1.1.dist-info/RECORD
