Metadata-Version: 2.4
Name: hatch-nodejs-build
Version: 1.1.1
Summary: Hatch build hook plugin for Node.js builds
Project-URL: Documentation, https://github.com/Helveg/hatch-nodejs-build?tab=readme-ov-file#hatch-nodejs-build
Project-URL: History, https://github.com/helveg/hatch-nodejs-build/commits/main
Project-URL: Issues, https://github.com/helveg/hatch-nodejs-build/issues
Project-URL: Source, https://github.com/helveg/hatch-nodejs-build
Author-email: Robin De Schepper <robin@alexandria.sc>
License-Expression: MIT
License-File: LICENSE.md
Keywords: app,build,hatch,node,nodejs,plugin,web
Classifier: Development Status :: 5 - Production/Stable
Classifier: Framework :: Hatch
Classifier: Programming Language :: Python
Classifier: Programming Language :: Python :: 3.9
Classifier: Programming Language :: Python :: 3.10
Classifier: Programming Language :: Python :: 3.11
Classifier: Programming Language :: Python :: 3.12
Classifier: Topic :: Software Development :: Build Tools
Requires-Python: >=3.9
Requires-Dist: black>=25.1.0
Requires-Dist: hatchling>=1.12.2
Requires-Dist: pydantic>=2.0
Requires-Dist: requests>=2.30.0
Requires-Dist: semantic-version>=2.10.0
